xsystem.py
xsystem-0.0.1.dist-info/LICENSE
xsystem-0.0.1.dist-info/METADATA
xsystem-0.0.1.dist-info/WHEEL
xsystem-0.0.1.dist-info/entry_points.txt
xsystem-0.0.1.dist-info/top_level.txt
xsystem-0.0.1.dist-info/RECORD
