Metadata-Version: 2.1
Name: xsystem
Version: 0.0.1
Summary: The project provides a tool/library implementing an automated regular expression building mechanism.
Home-page: https://github.com/IBM/regex-learner
Author: Stefano Braghin, Liubov Nedoshivina
Author-email: "Liubov Nedoshivia" <liubov.nedoshivina@ibm.com>
License: Apache License 2.0
Requires-Python: >=3.8
License-File: LICENSE
